{
  "info": {
    "name": "CareConnect API",
    "description": "API collection for CareConnect - Elderly Care Platform",
    "schema": "https://schema.getpostman.com/json/collection/v2.1.0/collection.json"
  },
  "item": [
    {
      "name": "Authentication",
      "item": [
        {
          "name": "Register",
          "request": {
            "method": "POST",
            "header": [
              {"key": "Content-Type", "value": "application/json"}
            ],
            "body": {
              "mode": "raw",
              "raw": "{\n  \"email\": \"newuser@example.com\",\n  \"password\": \"password123\",\n  \"first_name\": \"John\",\n  \"last_name\": \"Doe\",\n  \"phone\": \"0912345678\",\n  \"role\": \"volunteer\",\n  \"address\": \"123 Main Street\"\n}"
            },
            "url": {
              "raw": "{{base_url}}/api/auth/register",
              "host": ["{{base_url}}"],
              "path": ["api", "auth", "register"]
            }
          }
        },
        {
          "name": "Login",
          "request": {
            "method": "POST",
            "header": [
              {"key": "Content-Type", "value": "application/json"}
            ],
            "body": {
              "mode": "raw",
              "raw": "{\n  \"email\": \"test@example.com\",\n  \"password\": \"password123\"\n}"
            },
            "url": {
              "raw": "{{base_url}}/api/auth/login",
              "host": ["{{base_url}}"],
              "path": ["api", "auth", "login"]
            }
          }
        }
      ]
    },
    {
      "name": "Users",
      "item": [
        {
          "name": "Get User",
          "request": {
            "method": "GET",
            "header": [
              {"key": "Authorization", "value": "Bearer {{token}}"}
            ],
            "url": {
              "raw": "{{base_url}}/api/users/{{user_id}}",
              "host": ["{{base_url}}"],
              "path": ["api", "users", "{{user_id}}"]
            }
          }
        },
        {
          "name": "Update User",
          "request": {
            "method": "PUT",
            "header": [
              {"key": "Content-Type", "value": "application/json"},
              {"key": "Authorization", "value": "Bearer {{token}}"}
            ],
            "body": {
              "mode": "raw",
              "raw": "{\n  \"first_name\": \"Updated\",\n  \"phone\": \"0987654321\"\n}"
            },
            "url": {
              "raw": "{{base_url}}/api/users/{{user_id}}",
              "host": ["{{base_url}}"],
              "path": ["api", "users", "{{user_id}}"]
            }
          }
        },
        {
          "name": "Nearby Volunteers",
          "request": {
            "method": "GET",
            "header": [],
            "url": {
              "raw": "{{base_url}}/api/users/volunteers/nearby?latitude=10.8231&longitude=106.7038&radius=5",
              "host": ["{{base_url}}"],
              "path": ["api", "users", "volunteers", "nearby"],
              "query": [
                {"key": "latitude", "value": "10.8231"},
                {"key": "longitude", "value": "106.7038"},
                {"key": "radius", "value": "5"}
              ]
            }
          }
        }
      ]
    },
    {
      "name": "Service Requests",
      "item": [
        {
          "name": "Create Request",
          "request": {
            "method": "POST",
            "header": [
              {"key": "Content-Type", "value": "application/json"},
              {"key": "Authorization", "value": "Bearer {{token}}"}
            ],
            "body": {
              "mode": "raw",
              "raw": "{\n  \"elderly_id\": \"elderly-uuid\",\n  \"service_type\": \"medical\",\n  \"description\": \"Need medical check-up\",\n  \"preferred_date\": \"2024-03-25T10:00:00\"\n}"
            },
            "url": {
              "raw": "{{base_url}}/api/requests",
              "host": ["{{base_url}}"],
              "path": ["api", "requests"]
            }
          }
        },
        {
          "name": "Get Request",
          "request": {
            "method": "GET",
            "header": [
              {"key": "Authorization", "value": "Bearer {{token}}"}
            ],
            "url": {
              "raw": "{{base_url}}/api/requests/{{request_id}}",
              "host": ["{{base_url}}"],
              "path": ["api", "requests", "{{request_id}}"]
            }
          }
        },
        {
          "name": "Accept Request",
          "request": {
            "method": "POST",
            "header": [
              {"key": "Authorization", "value": "Bearer {{token}}"}
            ],
            "url": {
              "raw": "{{base_url}}/api/requests/{{request_id}}/accept",
              "host": ["{{base_url}}"],
              "path": ["api", "requests", "{{request_id}}", "accept"]
            }
          }
        },
        {
          "name": "Complete Request",
          "request": {
            "method": "POST",
            "header": [
              {"key": "Content-Type", "value": "application/json"},
              {"key": "Authorization", "value": "Bearer {{token}}"}
            ],
            "body": {
              "mode": "raw",
              "raw": "{\n  \"notes\": \"Service completed successfully. Patient was in good mood.\"\n}"
            },
            "url": {
              "raw": "{{base_url}}/api/requests/{{request_id}}/complete",
              "host": ["{{base_url}}"],
              "path": ["api", "requests", "{{request_id}}", "complete"]
            }
          }
        },
        {
          "name": "Rate Service",
          "request": {
            "method": "POST",
            "header": [
              {"key": "Content-Type", "value": "application/json"},
              {"key": "Authorization", "value": "Bearer {{token}}"}
            ],
            "body": {
              "mode": "raw",
              "raw": "{\n  \"rating\": 5,\n  \"feedback\": \"Excellent service!\",\n  \"tip\": 50000\n}"
            },
            "url": {
              "raw": "{{base_url}}/api/requests/{{request_id}}/rate",
              "host": ["{{base_url}}"],
              "path": ["api", "requests", "{{request_id}}", "rate"]
            }
          }
        },
        {
          "name": "My Requests",
          "request": {
            "method": "GET",
            "header": [
              {"key": "Authorization", "value": "Bearer {{token}}"}
            ],
            "url": {
              "raw": "{{base_url}}/api/requests/my-requests",
              "host": ["{{base_url}}"],
              "path": ["api", "requests", "my-requests"]
            }
          }
        }
      ]
    },
    {
      "name": "Payments",
      "item": [
        {
          "name": "Create Payment",
          "request": {
            "method": "POST",
            "header": [
              {"key": "Content-Type", "value": "application/json"},
              {"key": "Authorization", "value": "Bearer {{token}}"}
            ],
            "body": {
              "mode": "raw",
              "raw": "{\n  \"amount\": 100000,\n  \"payment_type\": \"service\",\n  \"currency\": \"VND\"\n}"
            },
            "url": {
              "raw": "{{base_url}}/api/payments",
              "host": ["{{base_url}}"],
              "path": ["api", "payments"]
            }
          }
        },
        {
          "name": "Get Payment",
          "request": {
            "method": "GET",
            "header": [
              {"key": "Authorization", "value": "Bearer {{token}}"}
            ],
            "url": {
              "raw": "{{base_url}}/api/payments/{{payment_id}}",
              "host": ["{{base_url}}"],
              "path": ["api", "payments", "{{payment_id}}"]
            }
          }
        },
        {
          "name": "Add Tip",
          "request": {
            "method": "POST",
            "header": [
              {"key": "Content-Type", "value": "application/json"},
              {"key": "Authorization", "value": "Bearer {{token}}"}
            ],
            "body": {
              "mode": "raw",
              "raw": "{\n  \"amount\": 50000\n}"
            },
            "url": {
              "raw": "{{base_url}}/api/payments/{{request_id}}/tip",
              "host": ["{{base_url}}"],
              "path": ["api", "payments", "{{request_id}}", "tip"]
            }
          }
        }
      ]
    },
    {
      "name": "Notifications",
      "item": [
        {
          "name": "Get Notifications",
          "request": {
            "method": "GET",
            "header": [
              {"key": "Authorization", "value": "Bearer {{token}}"}
            ],
            "url": {
              "raw": "{{base_url}}/api/notifications?limit=20&unread_only=false",
              "host": ["{{base_url}}"],
              "path": ["api", "notifications"],
              "query": [
                {"key": "limit", "value": "20"},
                {"key": "unread_only", "value": "false"}
              ]
            }
          }
        },
        {
          "name": "Mark as Read",
          "request": {
            "method": "POST",
            "header": [
              {"key": "Authorization", "value": "Bearer {{token}}"}
            ],
            "url": {
              "raw": "{{base_url}}/api/notifications/{{notification_id}}/mark-read",
              "host": ["{{base_url}}"],
              "path": ["api", "notifications", "{{notification_id}}", "mark-read"]
            }
          }
        }
      ]
    }
  ],
  "variable": [
    {
      "key": "base_url",
      "value": "http://localhost:5000",
      "type": "string"
    },
    {
      "key": "token",
      "value": "",
      "type": "string"
    },
    {
      "key": "user_id",
      "value": "",
      "type": "string"
    },
    {
      "key": "request_id",
      "value": "",
      "type": "string"
    },
    {
      "key": "payment_id",
      "value": "",
      "type": "string"
    },
    {
      "key": "notification_id",
      "value": "",
      "type": "string"
    }
  ]
}
